README.md
setup.cfg
setup.py
lorien/__init__.py
lorien/__main__.py
lorien/configs.py
lorien/logger.py
lorien/main.py
lorien/report.py
lorien/util.py
lorien/workload.py
lorien.egg-info/PKG-INFO
lorien.egg-info/SOURCES.txt
lorien.egg-info/dependency_links.txt
lorien.egg-info/requires.txt
lorien.egg-info/top_level.txt
lorien/database/__init__.py
lorien/database/commit.py
lorien/database/query.py
lorien/database/table.py
lorien/database/util.py
lorien/generate/__init__.py
lorien/generate/generator.py
lorien/generate/extract/__init__.py
lorien/generate/extract/extract.py
lorien/generate/extract/gcv.py
lorien/generate/extract/tf.py
lorien/generate/mutate/__init__.py
lorien/generate/mutate/modelzoo.py
lorien/generate/mutate/mutator.py
lorien/tune/__init__.py
lorien/tune/master.py
lorien/tune/tuner.py
lorien/tune/worker.py
lorien/tune/rpc/__init__.py
lorien/tune/rpc/client.py
lorien/tune/rpc/server.py
tests/__init__.py
tests/test_config.py
tests/test_database.py
tests/test_generate.py
tests/test_main.py
tests/test_tune.py
tests/test_workload.py