Metadata-Version: 2.1
Name: lorien
Version: 0.0.1
Summary: A Hyper-Automated Tuning System for Tensor Operators
Home-page: https://github.com/comaniac/lorien
Author: Cody Yu
Author-email: comaniac0422@gmail.com
License: Apache-2.0
Platform: UNKNOWN
Classifier: Development Status :: 3 - Alpha
Classifier: Intended Audience :: Developers
Classifier: Topic :: Software Development :: Build Tools
Classifier: License :: OSI Approved :: Apache Software License
Classifier: Programming Language :: Python :: 3
Classifier: Programming Language :: Python :: 3.6
